PyMTProxy-0.0.1.dev1.dist-info/METADATA
PyMTProxy-0.0.1.dev1.dist-info/RECORD
PyMTProxy-0.0.1.dev1.dist-info/WHEEL
PyMTProxy-0.0.1.dev1.dist-info/top_level.txt
mtproxy/__init__.py
